{
	"shopcar":[
		{
			"shopname":"韩都衣舍旗舰店",
			"shop":[
				{
					"title":"【3.30大牌日】韩都衣舍2019夏装新款女装韩版学生宽松印花圆领短袖",
					"price":"￥190.00",
					"src":"./images/shopcar1.jpg"
				}
			]
		},
		{
			"shopname":"当当网",
			"shop":[
				{
					"title":"Apple iPhone XS 256G 深空灰色 支持移动联通电信4G手机",
					"price":"￥8799.00",
					"src":"./images/shopcar2.jpg"
				},
				{
					"title":"我喜欢你，像风走了八千里（不要轻易取消订单，小当会按照下单先后顺）",
					"price":"￥34.40",
					"src":"./images/shopcar3.jpg"
				},
				{
					"title":"神奇校车大家族（全73册）",
					"price":"￥405.70",
					"src":"./images/shopcar4.jpg"
				}
			]
		}
		
	]
}